quick_db_connection/__init__.py
quick_db_connection/connection.py
quick_db_connection-1.0.dist-info/LICENSE
quick_db_connection-1.0.dist-info/METADATA
quick_db_connection-1.0.dist-info/WHEEL
quick_db_connection-1.0.dist-info/top_level.txt
quick_db_connection-1.0.dist-info/RECORD
