Metadata-Version: 2.2
Name: quick-db-connection
Version: 1.0
Summary: Módulo para gerenciamento de conexões com bancos de dados
Author-email: Bruno Sardou <bruno.sardou@outlook.com>
License: MIT
Project-URL: Homepage, https://github.com/bruno-sardou/quick-db-connection
Classifier: Programming Language :: Python :: 3
Classifier: License :: OSI Approved :: MIT License
Classifier: Operating System :: OS Independent
Requires-Python: >=3.8
License-File: LICENSE
Requires-Dist: pandas>=1.0.0
Requires-Dist: sqlalchemy>=1.4.0
Requires-Dist: pyodbc>=4.0.30
Requires-Dist: python-dotenv>=0.15.0
